README.md
setup.cfg
setup.py
uploader/__init__.py
uploader/clipboard.py
uploader/run.py
uploader/structure.py
uploader.egg-info/PKG-INFO
uploader.egg-info/SOURCES.txt
uploader.egg-info/dependency_links.txt
uploader.egg-info/entry_points.txt
uploader.egg-info/top_level.txt